[
  {
    "Name": "Normal",
    "IsBuiltIn": true,
    "IsModified": false,
    "IsQueue": false,
    "EncodingProfile": {
      "OutputFormat": "Mp4",
      "X264Tunes": [],
      "ContainerName": "av_mp4",
      "PreferredExtension": "Mp4",
      "IncludeChapterMarkers": false,
      "LargeFile": false,
      "Optimize": false,
      "IPod5GSupport": false,
      "SizingMode": "Automatic",
      "ScalingMode": "DownscaleOnly",
      "Width": 0,
      "Height": 0,
      "ScaleMethod": "Lanczos",
      "CustomCropping": false,
      "CroppingType": "Automatic",
      "Cropping": {
        "Top": 0,
        "Bottom": 0,
        "Left": 0,
        "Right": 0
      },
      "UseAnamorphic": true,
      "PixelAspectX": 0,
      "PixelAspectY": 0,
      "Modulus": 2,
      "Rotation": "None",
      "FlipHorizontal": false,
      "FlipVertical": false,
      "PaddingMode": "None", 
      "DeinterlaceType": "Off",
      "Detelecine": "off",
      "DenoiseType": "Off",
      "Deblock": 0,
      "Grayscale": false,
      "UseAdvancedTab": false,
      "VideoEncoder": "x264",
      "VideoOptions": "",
      "VideoProfile": "main",
      "VideoPreset": "veryfast",
      "VideoLevel": "4.0",
      "VideoTunes": [],
      "QsvDecode": false,
      "VideoEncodeRateType": "ConstantQuality",
      "Quality": 20.0,
      "TargetSize": 0,
      "VideoBitrate": 0,
      "TwoPass": false,
      "TurboFirstPass": false,
      "Framerate": 0.0,
      "ConstantFramerate": false,
      "PeakFramerate": false,
      "AudioEncodings": [
        {
          "InputNumber": 0,
          "Encoder": "av_aac",
          "PassthroughIfPossible": false,
          "EncodeRateType": "Bitrate",
          "Bitrate": 0,
          "Quality": 0.0,
          "Compression": -1.0,
          "Mixdown": "dpl2",
          "SampleRateRaw": 0,
          "Gain": 0,
          "Drc": 0.0
        }
      ]
    }
  },
  {
    "Name": "HighProfile",
    "IsBuiltIn": true,
    "IsModified": false,
    "IsQueue": false,
    "EncodingProfile": {
      "OutputFormat": "Mp4",
      "X264Tunes": [],
      "ContainerName": "av_mp4",
      "PreferredExtension": "Mp4",
      "IncludeChapterMarkers": false,
      "LargeFile": true,
      "Optimize": false,
      "IPod5GSupport": false,
      "SizingMode": "Automatic",
      "ScalingMode": "DownscaleOnly",
      "Width": 0,
      "Height": 0,
      "ScaleMethod": "Lanczos",
      "CustomCropping": false,
      "CroppingType": "Automatic",
      "Cropping": {
        "Top": 0,
        "Bottom": 0,
        "Left": 0,
        "Right": 0
      },
      "UseAnamorphic": true,
      "PixelAspectX": 0,
      "PixelAspectY": 0,
      "Modulus": 2,
      "Rotation": "None",
      "FlipHorizontal": false,
      "FlipVertical": false,
      "PaddingMode": "None", 
      "DeinterlaceType": "Decomb",
      "DeinterlacePreset": "default",
      "CombDetect": "default",
      "Detelecine": "off",
      "DenoiseType": "Off",
      "Deblock": 0,
      "Grayscale": false,
      "UseAdvancedTab": false,
      "VideoEncoder": "x264",
      "VideoOptions": "",
      "VideoProfile": "high",
      "VideoPreset": "medium",
      "VideoLevel": "4.1",
      "VideoTunes": [],
      "QsvDecode": false,
      "VideoEncodeRateType": "ConstantQuality",
      "Quality": 20.0,
      "TargetSize": 0,
      "VideoBitrate": 0,
      "TwoPass": false,
      "TurboFirstPass": false,
      "Framerate": 0.0,
      "ConstantFramerate": false,
      "PeakFramerate": false,
      "AudioEncodings": [
        {
          "InputNumber": 0,
          "Encoder": "av_aac",
          "PassthroughIfPossible": false,
          "EncodeRateType": "Bitrate",
          "Bitrate": 0,
          "Quality": 0.0,
          "Compression": -1.0,
          "Mixdown": "dpl2",
          "SampleRateRaw": 0,
          "Gain": 0,
          "Drc": 0.0
        },
        {
          "InputNumber": 0,
          "Encoder": "copy:ac3",
          "PassthroughIfPossible": false,
          "EncodeRateType": "Bitrate",
          "Bitrate": 0,
          "Quality": 0.0,
          "Compression": -1.0,
          "Mixdown": "dpl2",
          "SampleRateRaw": 0,
          "Gain": 0,
          "Drc": 0.0
        }
      ]
    }
  },
  {
    "Name": "Universal",
    "IsBuiltIn": true,
    "IsModified": false,
    "IsQueue": false,
    "EncodingProfile": {
      "OutputFormat": "Mp4",
      "X264Tunes": [],
      "ContainerName": "av_mp4",
      "PreferredExtension": 1,
      "IncludeChapterMarkers": true,
      "LargeFile": false,
      "Optimize": false,
      "IPod5GSupport": false,
      "SizingMode": "Automatic",
      "ScalingMode": "DownscaleOnly",
      "Width": 720,
      "Height": 0,
      "ScaleMethod": "Lanczos",
      "CustomCropping": false,
      "CroppingType": "Automatic",
      "Cropping": {
        "Top": 0,
        "Bottom": 0,
        "Left": 0,
        "Right": 0
      },
      "UseAnamorphic": true,
      "PixelAspectX": 0,
      "PixelAspectY": 0,
      "Modulus": 2,
      "Rotation": "None",
      "FlipHorizontal": false,
      "FlipVertical": false,
      "PaddingMode": "None", 
      "DeinterlaceType": "Off",
      "Detelecine": "off",
      "DenoiseType": "Off",
      "Deblock": 0,
      "Grayscale": false,
      "UseAdvancedTab": false,
      "VideoEncoder": "x264",
      "VideoOptions": "",
      "VideoProfile": "baseline",
      "VideoPreset": "fast",
      "VideoLevel": "3.0",
      "VideoTunes": [],
      "QsvDecode": false,
      "VideoEncodeRateType": "ConstantQuality",
      "Quality": 20.0,
      "TargetSize": 0,
      "VideoBitrate": 700,
      "TwoPass": false,
      "TurboFirstPass": false,
      "Framerate": 0.0,
      "ConstantFramerate": false,
      "PeakFramerate": false,
      "AudioEncodings": [
        {
          "InputNumber": 0,
          "Encoder": "av_aac",
          "PassthroughIfPossible": false,
          "EncodeRateType": "Bitrate",
          "Bitrate": 0,
          "Quality": 0.0,
          "Compression": -1.0,
          "Mixdown": "dpl2",
          "SampleRateRaw": 0,
          "Gain": 0,
          "Drc": 0.0
        },
        {
          "InputNumber": 0,
          "Encoder": "copy:ac3",
          "PassthroughIfPossible": false,
          "EncodeRateType": "Bitrate",
          "Bitrate": 0,
          "Quality": 0.0,
          "Compression": -1.0,
          "Mixdown": "dpl2",
          "SampleRateRaw": 0,
          "Gain": 0,
          "Drc": 0.0
        }
      ]
    }
  },
  {
    "Name": "Android",
    "IsBuiltIn": true,
    "IsModified": false,
    "IsQueue": false,
    "EncodingProfile": {
      "OutputFormat": "Mp4",
      "X264Tunes": [],
      "ContainerName": "av_mp4",
      "PreferredExtension": "Mp4",
      "IncludeChapterMarkers": false,
      "LargeFile": false,
      "Optimize": false,
      "IPod5GSupport": false,
      "SizingMode": "Automatic",
      "ScalingMode": "DownscaleOnly",
      "Width": 720,
      "Height": 0,
      "ScaleMethod": "Lanczos",
      "CustomCropping": false,
      "CroppingType": "Automatic",
      "Cropping": {
        "Top": 0,
        "Bottom": 0,
        "Left": 0,
        "Right": 0
      },
      "UseAnamorphic": true,
      "PixelAspectX": 99,
      "PixelAspectY": 100,
      "Modulus": 2,
      "Rotation": "None",
      "FlipHorizontal": false,
      "FlipVertical": false,
      "PaddingMode": "None", 
      "DeinterlaceType": "Off",
      "Detelecine": "off",
      "DenoiseType": "Off",
      "Deblock": 0,
      "Grayscale": false,
      "UseAdvancedTab": false,
      "VideoEncoder": "x264",
      "VideoOptions": "",
      "VideoProfile": "main",
      "VideoPreset": "medium",
      "VideoLevel": "2.2",
      "VideoTunes": [],
      "QsvDecode": false,
      "VideoEncodeRateType": "ConstantQuality",
      "Quality": 22.0,
      "TargetSize": 0,
      "VideoBitrate": 900,
      "TwoPass": false,
      "TurboFirstPass": false,
      "Framerate": 29.97,
      "ConstantFramerate": false,
      "PeakFramerate": false,
      "AudioEncodings": [
        {
          "InputNumber": 0,
          "Encoder": "av_aac",
          "PassthroughIfPossible": false,
          "EncodeRateType": "Bitrate",
          "Bitrate": 128,
          "Quality": 0.0,
          "Compression": -1.0,
          "Mixdown": "dpl2",
          "SampleRateRaw": 0,
          "Gain": 0,
          "Drc": 0.0
        }
      ]
    }
  },
  {
    "Name": "AndroidTablet",
    "IsBuiltIn": true,
    "IsModified": false,
    "IsQueue": false,
    "EncodingProfile": {
      "OutputFormat": "Mp4",
      "X264Tunes": [],
      "ContainerName": "av_mp4",
      "PreferredExtension": "Mp4",
      "IncludeChapterMarkers": false,
      "LargeFile": false,
      "Optimize": false,
      "IPod5GSupport": false,
      "SizingMode": "Automatic",
      "ScalingMode": "DownscaleOnly",
      "Width": 1280,
      "Height": 0,
      "ScaleMethod": "Lanczos",
      "CustomCropping": false,
      "CroppingType": "Automatic",
      "Cropping": {
        "Top": 0,
        "Bottom": 0,
        "Left": 0,
        "Right": 0
      },
      "UseAnamorphic": true,
      "PixelAspectX": 99,
      "PixelAspectY": 100,
      "Modulus": 2,
      "Rotation": "None",
      "FlipHorizontal": false,
      "FlipVertical": false,
      "PaddingMode": "None", 
      "DeinterlaceType": "Off",
      "Detelecine": "off",
      "DenoiseType": "Off",
      "Deblock": 0,
      "Grayscale": false,
      "UseAdvancedTab": false,
      "VideoEncoder": "x264",
      "VideoOptions": "",
      "VideoProfile": "main",
      "VideoPreset": "medium",
      "VideoLevel": "3.1",
      "VideoTunes": [],
      "QsvDecode": false,
      "VideoEncodeRateType": "ConstantQuality",
      "Quality": 22.0,
      "TargetSize": 110,
      "VideoBitrate": 900,
      "TwoPass": false,
      "TurboFirstPass": false,
      "Framerate": 29.97,
      "ConstantFramerate": false,
      "PeakFramerate": false,
      "AudioEncodings": [
        {
          "InputNumber": 0,
          "Encoder": "av_aac",
          "PassthroughIfPossible": false,
          "EncodeRateType": "Bitrate",
          "Bitrate": 128,
          "Quality": 0.0,
          "Compression": -1.0,
          "Mixdown": "dpl2",
          "SampleRateRaw": 0,
          "Gain": 0,
          "Drc": 0.0
        }
      ]
    }
  },
  {
    "Name": "AppleiPod",
    "IsBuiltIn": true,
    "IsModified": false,
    "IsQueue": false,
    "EncodingProfile": {
      "OutputFormat": "Mp4",
      "X264Tunes": [],
      "ContainerName": "av_mp4",
      "PreferredExtension": "Mp4",
      "IncludeChapterMarkers": true,
      "LargeFile": false,
      "Optimize": false,
      "IPod5GSupport": true,
      "SizingMode": "Automatic",
      "ScalingMode": "DownscaleOnly",
      "Width": 320,
      "Height": 0,
      "ScaleMethod": "Lanczos",
      "CustomCropping": false,
      "CroppingType": "Automatic",
      "Cropping": {
        "Top": 0,
        "Bottom": 0,
        "Left": 0,
        "Right": 0
      },
      "UseAnamorphic": false,
      "PixelAspectX": 0,
      "PixelAspectY": 0,
      "Modulus": 2,
      "Rotation": "None",
      "FlipHorizontal": false,
      "FlipVertical": false,
      "PaddingMode": "None", 
      "DeinterlaceType": "Off",
      "Detelecine": "off",
      "DenoiseType": "Off",
      "Deblock": 0,
      "Grayscale": false,
      "UseAdvancedTab": false,
      "VideoEncoder": "x264",
      "VideoOptions": "",
      "VideoProfile": "baseline",
      "VideoPreset": "medium",
      "VideoLevel": "1.3",
      "VideoTunes": [],
      "QsvDecode": false,
      "VideoEncodeRateType": "ConstantQuality",
      "Quality": 22.0,
      "TargetSize": 0,
      "VideoBitrate": 700,
      "TwoPass": false,
      "TurboFirstPass": false,
      "Framerate": 0.0,
      "ConstantFramerate": false,
      "PeakFramerate": false,
      "AudioEncodings": [
        {
          "InputNumber": 0,
          "Encoder": "av_aac",
          "PassthroughIfPossible": false,
          "EncodeRateType": "Bitrate",
          "Bitrate": 0,
          "Quality": 0.0,
          "Compression": -1.0,
          "Mixdown": "dpl2",
          "SampleRateRaw": 0,
          "Gain": 0,
          "Drc": 0.0
        }
      ]
    }
  },
  {
    "Name": "AppleiPhoneTouch",
    "IsBuiltIn": true,
    "IsModified": false,
    "IsQueue": false,
    "EncodingProfile": {
      "OutputFormat": "Mp4",
      "X264Tunes": [],
      "ContainerName": "av_mp4",
      "PreferredExtension": "Mp4",
      "IncludeChapterMarkers": true,
      "LargeFile": false,
      "Optimize": false,
      "IPod5GSupport": false,
      "SizingMode": "Automatic",
      "ScalingMode": "DownscaleOnly",
      "Width": 960,
      "Height": 0,
      "ScaleMethod": "Lanczos",
      "CustomCropping": false,
      "CroppingType": "Automatic",
      "Cropping": {
        "Top": 0,
        "Bottom": 0,
        "Left": 0,
        "Right": 0
      },
      "UseAnamorphic": true,
      "PixelAspectX": 0,
      "PixelAspectY": 0,
      "Modulus": 2,
      "Rotation": "None",
      "FlipHorizontal": false,
      "FlipVertical": false,
      "PaddingMode": "None", 
      "DeinterlaceType": "Off",
      "Detelecine": "off",
      "DenoiseType": "Off",
      "Deblock": 0,
      "Grayscale": false,
      "UseAdvancedTab": false,
      "VideoEncoder": "x264",
      "VideoOptions": "",
      "VideoProfile": "high",
      "VideoPreset": "medium",
      "VideoLevel": "3.1",
      "VideoTunes": [],
      "QsvDecode": false,
      "VideoEncodeRateType": "ConstantQuality",
      "Quality": 22.0,
      "TargetSize": 0,
      "VideoBitrate": 0,
      "TwoPass": false,
      "TurboFirstPass": false,
      "Framerate": 0.0,
      "ConstantFramerate": false,
      "PeakFramerate": false,
      "AudioEncodings": [
        {
          "InputNumber": 0,
          "Encoder": "av_aac",
          "PassthroughIfPossible": false,
          "EncodeRateType": "Bitrate",
          "Bitrate": 128,
          "Quality": 0.0,
          "Compression": -1.0,
          "Mixdown": "dpl2",
          "SampleRateRaw": 0,
          "Gain": 0,
          "Drc": 0.0
        }
      ]
    }
  },
  {
    "Name": "AppleiPhone4",
    "IsBuiltIn": true,
    "IsModified": false,
    "IsQueue": false,
    "EncodingProfile": {
      "OutputFormat": "Mp4",
      "X264Tunes": [],
      "ContainerName": "av_mp4",
      "PreferredExtension": "Mp4",
      "IncludeChapterMarkers": true,
      "LargeFile": true,
      "Optimize": false,
      "IPod5GSupport": false,
      "SizingMode": "Automatic",
      "ScalingMode": "DownscaleOnly",
      "Width": 960,
      "Height": 0,
      "ScaleMethod": "Lanczos",
      "CustomCropping": false,
      "CroppingType": "Automatic",
      "Cropping": {
        "Top": 0,
        "Bottom": 0,
        "Left": 0,
        "Right": 0
      },
      "UseAnamorphic": true,
      "PixelAspectX": 0,
      "PixelAspectY": 0,
      "Modulus": 16,
      "Rotation": "None",
      "FlipHorizontal": false,
      "FlipVertical": false,
      "PaddingMode": "None", 
      "DeinterlaceType": "Off",
      "Detelecine": "off",
      "DenoiseType": "Off",
      "Deblock": 0,
      "Grayscale": false,
      "UseAdvancedTab": false,
      "VideoEncoder": "x264",
      "VideoOptions": "",
      "VideoTunes": [],
      "QsvDecode": false,
      "VideoEncodeRateType": "ConstantQuality",
      "Quality": 20.0,
      "TargetSize": 0,
      "VideoBitrate": 0,
      "TwoPass": false,
      "TurboFirstPass": false,
      "Framerate": 29.97,
      "ConstantFramerate": false,
      "PeakFramerate": false,
      "AudioEncodings": [
        {
          "InputNumber": 0,
          "Encoder": "av_aac",
          "PassthroughIfPossible": false,
          "EncodeRateType": "Bitrate",
          "Bitrate": 0,
          "Quality": 0.0,
          "Compression": -1.0,
          "Mixdown": "dpl2",
          "SampleRateRaw": 0,
          "Gain": 0,
          "Drc": 0.0
        }
      ]
    }
  },
  {
    "Name": "AppleiPad",
    "IsBuiltIn": true,
    "IsModified": false,
    "IsQueue": false,
    "EncodingProfile": {
      "OutputFormat": "Mp4",
      "X264Tunes": [],
      "ContainerName": "av_mp4",
      "PreferredExtension": "Mp4",
      "IncludeChapterMarkers": true,
      "LargeFile": true,
      "Optimize": false,
      "IPod5GSupport": false,
      "SizingMode": "Automatic",
      "ScalingMode": "DownscaleOnly",
      "Width": 1280,
      "Height": 0,
      "ScaleMethod": "Lanczos",
      "CustomCropping": false,
      "CroppingType": "Automatic",
      "Cropping": {
        "Top": 0,
        "Bottom": 0,
        "Left": 0,
        "Right": 0
      },
      "UseAnamorphic": true,
      "PixelAspectX": 0,
      "PixelAspectY": 0,
      "Modulus": 2,
      "Rotation": "None",
      "FlipHorizontal": false,
      "FlipVertical": false,
      "PaddingMode": "None", 
      "DeinterlaceType": "Off",
      "Detelecine": "off",
      "DenoiseType": "Off",
      "Deblock": 0,
      "Grayscale": false,
      "UseAdvancedTab": false,
      "VideoEncoder": "x264",
      "VideoOptions": "",
      "VideoProfile": "high",
      "VideoPreset": "medium",
      "VideoLevel": "3.1",
      "VideoTunes": [],
      "QsvDecode": false,
      "VideoEncodeRateType": "ConstantQuality",
      "Quality": 20.0,
      "TargetSize": 0,
      "VideoBitrate": 0,
      "TwoPass": false,
      "TurboFirstPass": false,
      "Framerate": 29.97,
      "ConstantFramerate": false,
      "PeakFramerate": false,
      "AudioEncodings": [
        {
          "InputNumber": 0,
          "Encoder": "av_aac",
          "PassthroughIfPossible": false,
          "EncodeRateType": "Bitrate",
          "Bitrate": 0,
          "Quality": 0.0,
          "Compression": -1.0,
          "Mixdown": "dpl2",
          "SampleRateRaw": 0,
          "Gain": 0,
          "Drc": 0.0
        }
      ]
    }
  },
  {
    "Name": "AppleTV",
    "IsBuiltIn": true,
    "IsModified": false,
    "IsQueue": false,
    "EncodingProfile": {
      "OutputFormat": "Mp4",
      "X264Tunes": [],
      "ContainerName": "av_mp4",
      "PreferredExtension": 1,
      "IncludeChapterMarkers": true,
      "LargeFile": true,
      "Optimize": false,
      "IPod5GSupport": false,
      "SizingMode": "Automatic",
      "ScalingMode": "DownscaleOnly",
      "Width": 960,
      "Height": 0,
      "ScaleMethod": "Lanczos",
      "CustomCropping": false,
      "CroppingType": "Automatic",
      "Cropping": {
        "Top": 0,
        "Bottom": 0,
        "Left": 0,
        "Right": 0
      },
      "UseAnamorphic": true,
      "PixelAspectX": 0,
      "PixelAspectY": 0,
      "Modulus": 2,
      "Rotation": "None",
      "FlipHorizontal": false,
      "FlipVertical": false,
      "PaddingMode": "None", 
      "DeinterlaceType": "Off",
      "Detelecine": "off",
      "DenoiseType": "Off",
      "Deblock": 0,
      "Grayscale": false,
      "UseAdvancedTab": false,
      "VideoEncoder": "x264",
      "VideoOptions": "cabac=0:weightb=0:weightp=0:vbv-maxrate=9500:vbv-bufsize=9500:b-pyramid=none:ref=2",
      "VideoProfile": "main",
      "VideoPreset": "medium",
      "VideoLevel": "3.1",
      "VideoTunes": [],
      "QsvDecode": false,
      "VideoEncodeRateType": "ConstantQuality",
      "Quality": 20.0,
      "TargetSize": 0,
      "VideoBitrate": 700,
      "TwoPass": false,
      "TurboFirstPass": false,
      "Framerate": 0.0,
      "ConstantFramerate": false,
      "PeakFramerate": false,
      "AudioEncodings": [
        {
          "InputNumber": 0,
          "Encoder": "av_aac",
          "PassthroughIfPossible": false,
          "EncodeRateType": "Bitrate",
          "Bitrate": 0,
          "Quality": 0.0,
          "Compression": -1.0,
          "Mixdown": "dpl2",
          "SampleRateRaw": 0,
          "Gain": 0,
          "Drc": 0.0
        },
        {
          "InputNumber": 0,
          "Encoder": "copy:ac3",
          "PassthroughIfPossible": false,
          "EncodeRateType": "Bitrate",
          "Bitrate": 0,
          "Quality": 0.0,
          "Compression": -1.0,
          "Mixdown": "dpl2",
          "SampleRateRaw": 0,
          "Gain": 0,
          "Drc": 0.0
        }
      ]
    }
  },
  {
    "Name": "AppleTV2",
    "IsBuiltIn": true,
    "IsModified": false,
    "IsQueue": false,
    "EncodingProfile": {
      "OutputFormat": "Mp4",
      "X264Tunes": [],
      "ContainerName": "av_mp4",
      "PreferredExtension": 1,
      "IncludeChapterMarkers": true,
      "LargeFile": true,
      "Optimize": false,
      "IPod5GSupport": false,
      "SizingMode": "Automatic",
      "ScalingMode": "DownscaleOnly",
      "Width": 1280,
      "Height": 0,
      "ScaleMethod": "Lanczos",
      "CustomCropping": false,
      "CroppingType": "Automatic",
      "Cropping": {
        "Top": 0,
        "Bottom": 0,
        "Left": 0,
        "Right": 0
      },
      "UseAnamorphic": true,
      "PixelAspectX": 0,
      "PixelAspectY": 0,
      "Modulus": 2,
      "Rotation": "None",
      "FlipHorizontal": false,
      "FlipVertical": false,
      "PaddingMode": "None", 
      "DeinterlaceType": "Off",
      "Detelecine": "off",
      "DenoiseType": "Off",
      "Deblock": 0,
      "Grayscale": false,
      "UseAdvancedTab": false,
      "VideoEncoder": "x264",
      "VideoOptions": "",
      "VideoProfile": "high",
      "VideoPreset": "medium",
      "VideoLevel": "3.1",
      "VideoTunes": [],
      "QsvDecode": false,
      "VideoEncodeRateType": "ConstantQuality",
      "Quality": 20.0,
      "TargetSize": 0,
      "VideoBitrate": 700,
      "TwoPass": false,
      "TurboFirstPass": false,
      "Framerate": 29.97,
      "ConstantFramerate": false,
      "PeakFramerate": false,
      "AudioEncodings": [
        {
          "InputNumber": 0,
          "Encoder": "av_aac",
          "PassthroughIfPossible": false,
          "EncodeRateType": "Bitrate",
          "Bitrate": 0,
          "Quality": 0.0,
          "Compression": -1.0,
          "Mixdown": "dpl2",
          "SampleRateRaw": 0,
          "Gain": 0,
          "Drc": 0.0
        },
        {
          "InputNumber": 0,
          "Encoder": "copy:ac3",
          "PassthroughIfPossible": false,
          "EncodeRateType": "Bitrate",
          "Bitrate": 0,
          "Quality": 0.0,
          "Compression": -1.0,
          "Mixdown": "dpl2",
          "SampleRateRaw": 0,
          "Gain": 0,
          "Drc": 0.0
        }
      ]
    }
  },
  {
    "Name": "AppleTV3",
    "IsBuiltIn": true,
    "IsModified": false,
    "IsQueue": false,
    "EncodingProfile": {
      "OutputFormat": "Mp4",
      "X264Tunes": [],
      "ContainerName": "av_mp4",
      "PreferredExtension": 1,
      "IncludeChapterMarkers": true,
      "LargeFile": true,
      "Optimize": false,
      "IPod5GSupport": false,
      "SizingMode": "Automatic",
      "ScalingMode": "DownscaleOnly",
      "Width": 1920,
      "Height": 0,
      "ScaleMethod": "Lanczos",
      "CustomCropping": false,
      "CroppingType": "Automatic",
      "Cropping": {
        "Top": 0,
        "Bottom": 0,
        "Left": 0,
        "Right": 0
      },
      "UseAnamorphic": true,
      "PixelAspectX": 0,
      "PixelAspectY": 0,
      "Modulus": 2,
      "Rotation": "None",
      "FlipHorizontal": false,
      "FlipVertical": false,
      "PaddingMode": "None", 
      "DeinterlaceType": "Off",
      "Detelecine": "off",
      "DenoiseType": "Off",
      "Deblock": 0,
      "Grayscale": false,
      "UseAdvancedTab": false,
      "VideoEncoder": "x264",
      "VideoOptions": "",
      "VideoProfile": "high",
      "VideoPreset": "medium",
      "VideoLevel": "4.0",
      "VideoTunes": [],
      "QsvDecode": false,
      "VideoEncodeRateType": "ConstantQuality",
      "Quality": 20.0,
      "TargetSize": 0,
      "VideoBitrate": 700,
      "TwoPass": false,
      "TurboFirstPass": false,
      "Framerate": 0.0,
      "ConstantFramerate": false,
      "PeakFramerate": false,
      "AudioEncodings": [
        {
          "InputNumber": 0,
          "Encoder": "av_aac",
          "PassthroughIfPossible": false,
          "EncodeRateType": "Bitrate",
          "Bitrate": 0,
          "Quality": 0.0,
          "Compression": -1.0,
          "Mixdown": "dpl2",
          "SampleRateRaw": 0,
          "Gain": 0,
          "Drc": 0.0
        },
        {
          "InputNumber": 0,
          "Encoder": "copy:ac3",
          "PassthroughIfPossible": false,
          "EncodeRateType": "Bitrate",
          "Bitrate": 0,
          "Quality": 0.0,
          "Compression": -1.0,
          "Mixdown": "dpl2",
          "SampleRateRaw": 0,
          "Gain": 0,
          "Drc": 0.0
        }
      ]
    }
  },
  {
    "Name": "WindowsPhone7",
    "IsBuiltIn": true,
    "IsModified": false,
    "IsQueue": false,
    "EncodingProfile": {
      "OutputFormat": "Mp4",
      "X264Tunes": [],
      "ContainerName": "av_mp4",
      "PreferredExtension": "Mp4",
      "IncludeChapterMarkers": false,
      "LargeFile": false,
      "Optimize": false,
      "IPod5GSupport": false,
      "SizingMode": "Automatic",
      "ScalingMode": "DownscaleOnly",
      "Width": 800,
      "Height": 480,
      "ScaleMethod": "Lanczos",
      "CustomCropping": false,
      "CroppingType": "Automatic",
      "Cropping": {
        "Top": 0,
        "Bottom": 0,
        "Left": 0,
        "Right": 0
      },
      "UseAnamorphic": false,
      "PixelAspectX": 0,
      "PixelAspectY": 0,
      "Modulus": 16,
      "Rotation": "None",
      "FlipHorizontal": false,
      "FlipVertical": false,
      "PaddingMode": "None", 
      "DeinterlaceType": "Off",
      "Detelecine": "off",
      "DenoiseType": "Off",
      "Deblock": 0,
      "Grayscale": false,
      "UseAdvancedTab": false,
      "VideoEncoder": "x264",
      "VideoOptions": "ref=2:mixed-refs=0:bframes=2:weightb=0:subq=6:8x8dct=0:trellis=0",
      "VideoTunes": [],
      "QsvDecode": false,
      "VideoEncodeRateType": "ConstantQuality",
      "Quality": 20.0,
      "TargetSize": 700,
      "VideoBitrate": 1200,
      "TwoPass": false,
      "TurboFirstPass": false,
      "Framerate": 0.0,
      "ConstantFramerate": false,
      "PeakFramerate": false,
      "AudioEncodings": [
        {
          "InputNumber": 0,
          "Encoder": "av_aac",
          "PassthroughIfPossible": false,
          "EncodeRateType": "Bitrate",
          "Bitrate": 128,
          "Quality": 0.0,
          "Compression": -1.0,
          "Mixdown": "stereo",
          "SampleRateRaw": 0,
          "Gain": 0,
          "Drc": 0.0
        }
      ]
    }
  },
  {
    "Name": "WindowsPhone8",
    "IsBuiltIn": true,
    "IsModified": false,
    "IsQueue": false,
    "EncodingProfile": {
      "OutputFormat": "Mp4",
      "X264Tunes": [],
      "ContainerName": "av_mp4",
      "PreferredExtension": "Mp4",
      "IncludeChapterMarkers": false,
      "LargeFile": true,
      "Optimize": false,
      "IPod5GSupport": false,
      "SizingMode": "Automatic",
      "ScalingMode": "DownscaleOnly",
      "Width": 1280,
      "Height": 720,
      "ScaleMethod": "Lanczos",
      "CustomCropping": false,
      "CroppingType": "Automatic",
      "Cropping": {
        "Top": 0,
        "Bottom": 0,
        "Left": 0,
        "Right": 0
      },
      "UseAnamorphic": false,
      "PixelAspectX": 0,
      "PixelAspectY": 0,
      "Modulus": 16,
      "Rotation": "None",
      "FlipHorizontal": false,
      "FlipVertical": false,
      "PaddingMode": "None", 
      "DeinterlaceType": "Off",
      "Detelecine": "off",
      "DenoiseType": "Off",
      "Deblock": 0,
      "Grayscale": false,
      "UseAdvancedTab": false,
      "VideoEncoder": "x264",
      "VideoOptions": "",
      "VideoTunes": [],
      "QsvDecode": false,
      "VideoEncodeRateType": "ConstantQuality",
      "Quality": 20.0,
      "TargetSize": 700,
      "VideoBitrate": 1200,
      "TwoPass": false,
      "TurboFirstPass": false,
      "Framerate": 0.0,
      "ConstantFramerate": false,
      "PeakFramerate": false,
      "AudioEncodings": [
        {
          "InputNumber": 0,
          "Encoder": "av_aac",
          "PassthroughIfPossible": false,
          "EncodeRateType": "Bitrate",
          "Bitrate": 0,
          "Quality": 0.0,
          "Compression": -1.0,
          "Mixdown": "dpl2",
          "SampleRateRaw": 0,
          "Gain": 0,
          "Drc": 0.0
        }
      ]
    }
  },
  {
    "Name": "Xbox360",
    "IsBuiltIn": true,
    "IsModified": false,
    "IsQueue": false,
    "EncodingProfile": {
      "OutputFormat": "Mp4",
      "X264Tunes": [],
      "ContainerName": "av_mp4",
      "PreferredExtension": "Mp4",
      "IncludeChapterMarkers": false,
      "LargeFile": false,
      "Optimize": false,
      "IPod5GSupport": false,
      "SizingMode": "Automatic",
      "ScalingMode": "DownscaleOnly",
      "Width": 0,
      "Height": 0,
      "ScaleMethod": "Lanczos",
      "CustomCropping": false,
      "CroppingType": "Automatic",
      "Cropping": {
        "Top": 0,
        "Bottom": 0,
        "Left": 0,
        "Right": 0
      },
      "UseAnamorphic": true,
      "PixelAspectX": 0,
      "PixelAspectY": 0,
      "Modulus": 2,
      "Rotation": "None",
      "FlipHorizontal": false,
      "FlipVertical": false,
      "PaddingMode": "None", 
      "DeinterlaceType": "Decomb",
      "DeinterlacePreset": "default",
      "CombDetect": "default",
      "Detelecine": "off",
      "DenoiseType": "Off",
      "Deblock": 0,
      "Grayscale": false,
      "UseAdvancedTab": false,
      "VideoEncoder": "x264",
      "VideoOptions": "",
      "VideoProfile": "high",
      "VideoPreset": "medium",
      "VideoLevel": "4.1",
      "VideoTunes": [],
      "QsvDecode": false,
      "VideoEncodeRateType": "ConstantQuality",
      "Quality": 20.0,
      "TargetSize": 4096,
      "VideoBitrate": 1156,
      "TwoPass": false,
      "TurboFirstPass": false,
      "Framerate": 30.0,
      "ConstantFramerate": false,
      "PeakFramerate": false,
      "AudioEncodings": [
        {
          "InputNumber": 0,
          "Encoder": "copy:ac3",
          "PassthroughIfPossible": false,
          "EncodeRateType": "Bitrate",
          "Bitrate": 0,
          "Quality": 0.0,
          "Compression": -1.0,
          "SampleRateRaw": 0,
          "Gain": 0,
          "Drc": 0.0
        },
        {
          "InputNumber": 0,
          "Encoder": "av_aac",
          "PassthroughIfPossible": false,
          "EncodeRateType": "Bitrate",
          "Bitrate": 0,
          "Quality": 0.0,
          "Compression": -1.0,
          "Mixdown": "dpl2",
          "SampleRateRaw": 0,
          "Gain": 0,
          "Drc": 0.0
        }
      ]
    }
  }
]